analysisstore/__init__.py
analysisstore/_version.py
analysisstore/api.py
analysisstore/ignition.py
analysisstore/client/__init__.py
analysisstore/client/asutils.py
analysisstore/client/commands.py
analysisstore/client/conf.py
analysisstore/client/local_commands.py
analysisstore/server/__init__.py
analysisstore/server/astore.py
analysisstore/server/conf.py
analysisstore/server/engine.py
analysisstore/server/utils.py
analysisstore/test/__init__.py
analysisstore/test/test_api_smoke.py
analysisstore/test/test_client.py
analysisstore/test/test_conn_pool.py
analysisstore/test/testing.py
analysisstore-0.0.6.dist-info/LICENSE
analysisstore-0.0.6.dist-info/METADATA
analysisstore-0.0.6.dist-info/WHEEL
analysisstore-0.0.6.dist-info/top_level.txt
analysisstore-0.0.6.dist-info/RECORD
